{
	"id": "chattask-unified-env-2024",
	"name": "ChatTask Unified System Environment",
	"values": [
		{
			"key": "userBase",
			"value": "http://localhost:5001",
			"type": "default",
			"enabled": true,
			"description": "User Service base URL"
		},
		{
			"key": "authBase",
			"value": "http://localhost:5003",
			"type": "default",
			"enabled": true,
			"description": "Auth Service base URL"
		},
		{
			"key": "chatBase",
			"value": "http://localhost:5002",
			"type": "default",
			"enabled": true,
			"description": "Chat Service base URL"
		},
		{
			"key": "taskBase",
			"value": "http://localhost:5004",
			"type": "default",
			"enabled": true,
			"description": "Task Service base URL"
		},
		{
			"key": "accessToken",
			"value": "",
			"type": "default",
			"enabled": true,
			"description": "JWT access token for authentication"
		},
		{
			"key": "currentUsername",
			"value": "",
			"type": "default",
			"enabled": true,
			"description": "Currently logged in username"
		},
		{
			"key": "currentUserId",
			"value": "",
			"type": "default",
			"enabled": true,
			"description": "Currently logged in user ID"
		},
		{
			"key": "workspaceId",
			"value": "",
			"type": "default",
			"enabled": true,
			"description": "Current workspace ID"
		},
		{
			"key": "workspaceName",
			"value": "",
			"type": "default",
			"enabled": true,
			"description": "Current workspace name"
		},
		{
			"key": "channelId",
			"value": "",
			"type": "default",
			"enabled": true,
			"description": "Current channel ID"
		},
		{
			"key": "channelName",
			"value": "",
			"type": "default",
			"enabled": true,
			"description": "Current channel name"
		},
		{
			"key": "groupId",
			"value": "",
			"type": "default",
			"enabled": true,
			"description": "Current group ID"
		},
		{
			"key": "groupName",
			"value": "",
			"type": "default",
			"enabled": true,
			"description": "Current group name"
		},
		{
			"key": "dmId",
			"value": "",
			"type": "default",
			"enabled": true,
			"description": "Current direct message ID"
		},
		{
			"key": "userId1",
			"value": "",
			"type": "default",
			"enabled": true,
			"description": "First test user ID"
		},
		{
			"key": "userId2",
			"value": "",
			"type": "default",
			"enabled": true,
			"description": "Second test user ID"
		},
		{
			"key": "workspaceMemberId",
			"value": "",
			"type": "default",
			"enabled": true,
			"description": "Workspace member ID"
		},
		{
			"key": "channelMemberId",
			"value": "",
			"type": "default",
			"enabled": true,
			"description": "Channel member ID"
		},
		{
			"key": "lastMessageId",
			"value": "",
			"type": "default",
			"enabled": true,
			"description": "Last sent message ID"
		},
		{
			"key": "messageContent",
			"value": "",
			"type": "default",
			"enabled": true,
			"description": "Last message content"
		}
	],
	"_postman_variable_scope": "environment",
	"_postman_exported_at": "2024-09-09T12:00:00.000Z",
	"_postman_exported_using": "Postman/10.0.0"
}
